[
	{
		"mac": "0004fbf4ea0f",
		"kind": 17,
		"timestamp": 1740988365000,
		"items": {
			"18": 0.0,
			"14": 0.0,
			"12": 0.0,
			"0": 1,
			"1": 113.985946,
			"13": 0,
			"11": 0,
			"16": 0.0,
			"17": 0,
			"2": 22.686858,
			"3": 11.3,
			"15": 0
		}
	},
	{
		"mac": "0004fbf4ea0f",
		"kind": 17,
		"timestamp": 1740988366000,
		"items": {
			"13": 16533,
			"11": 16523,
			"18": -69.0,
			"3": 11.3,
			"2": 100.0,
			"0": 21,
			"14": -62.0,
			"1": 113.985946,
			"15": 16515,
			"12": -59.0,
			"16": -62.0,
			"17": 16534
		}
	},
	{
		"mac": "0004fbf4ea0f",
		"kind": 17,
		"timestamp": 1740988369000,
		"items": {
			"18": -66.0,
			"2": 100.0,
			"0": 21,
			"3": 11.3,
			"12": -63.0,
			"13": 16533,
			"11": 16523,
			"14": -65.0,
			"1": 113.985946,
			"15": 16515,
			"16": -65.0,
			"17": 16524
		}
	},
	{
		"mac": "0004fbf4ea0f",
		"kind": 17,
		"timestamp": 1740988372000,
		"items": {
			"3": 11.3,
			"11": 16523,
			"2": 100.0,
			"12": -69.0,
			"13": 16515,
			"1": 113.985946,
			"14": -71.0,
			"18": -75.0,
			"17": 12575,
			"15": 16533,
			"16": -75.0,
			"0": 21
		}
	},
	{
		"mac": "0004fbf4ea0f",
		"kind": 17,
		"timestamp": 1740988375000,
		"items": {
			"16": -68.0,
			"2": 100.0,
			"15": 16533,
			"1": 113.985942,
			"3": 11.4,
			"12": -65.0,
			"0": 21,
			"13": 12575,
			"11": 16524,
			"17": 12583,
			"14": -67.0,
			"18": -74.0
		}
	},
	{
		"mac": "0004fbf4ea0f",
		"kind": 17,
		"timestamp": 1740988378000,
		"items": {
			"14": -64.0,
			"3": 11.4,
			"18": -67.0,
			"0": 21,
			"2": 100.0,
			"12": -61.0,
			"11": 16523,
			"15": 12575,
			"17": 16524,
			"16": -65.0,
			"13": 16533,
			"1": 113.985943
		}
	},
	{
		"mac": "0004fbf4ea0f",
		"kind": 17,
		"timestamp": 1740988381000,
		"items": {
			"14": -68.0,
			"15": 12575,
			"17": 16533,
			"18": -68.0,
			"12": -67.0,
			"3": 11.4,
			"1": 113.985944,
			"16": -68.0,
			"13": 12574,
			"0": 21,
			"2": 100.0,
			"11": 16524
		}
	},
	{
		"mac": "0004fbf4ea0f",
		"kind": 17,
		"timestamp": 1740988384000,
		"items": {
			"16": -67.0,
			"18": -68.0,
			"3": 11.3,
			"12": -61.0,
			"17": 12574,
			"11": 16524,
			"0": 21,
			"13": 12570,
			"14": -65.0,
			"1": 113.985944,
			"2": 100.0,
			"15": 12571
		}
	},
	{
		"mac": "0004fbf4ea0f",
		"kind": 17,
		"timestamp": 1740988387000,
		"items": {
			"3": 11.3,
			"13": 12574,
			"16": -62.0,
			"18": -65.0,
			"14": -62.0,
			"17": 12571,
			"0": 21,
			"15": 12570,
			"11": 12582,
			"2": 100.0,
			"12": -56.0,
			"1": 113.985944
		}
	},
	{
		"mac": "0004fbf4ea0f",
		"kind": 17,
		"timestamp": 1740988390000,
		"items": {
			"14": -62.0,
			"2": 100.0,
			"15": 12571,
			"0": 21,
			"16": -65.0,
			"3": 11.3,
			"17": 12578,
			"1": 113.985944,
			"13": 12570,
			"18": -65.0,
			"11": 12574,
			"12": -56.0
		}
	},
	{
		"mac": "0004fbf4ea0f",
		"kind": 17,
		"timestamp": 1740988393000,
		"items": {
			"13": 12587,
			"16": -73.0,
			"0": 21,
			"17": 12588,
			"12": -68.0,
			"2": 100.0,
			"15": 16515,
			"3": 11.3,
			"14": -69.0,
			"11": 12589,
			"1": 113.985945,
			"18": -77.0
		}
	},
	{
		"mac": "0004fbf4ea0f",
		"kind": 17,
		"timestamp": 1740988396000,
		"items": {
			"1": 113.985945,
			"0": 21,
			"11": 12589,
			"12": -68.0,
			"15": 12577,
			"16": -77.0,
			"2": 100.0,
			"13": 12581,
			"3": 11.3,
			"14": -73.0,
			"18": -78.0,
			"17": 12572
		}
	},
	{
		"mac": "0004fbf4ea0f",
		"kind": 17,
		"timestamp": 1740988399000,
		"items": {
			"1": 113.985946,
			"0": 21,
			"2": 100.0,
			"3": 11.3,
			"14": -71.0,
			"13": 12587,
			"11": 12589,
			"12": -71.0,
			"15": 12577,
			"16": -74.0,
			"17": 12581,
			"18": -76.0
		}
	},
	{
		"mac": "0004fbf4ea0f",
		"kind": 17,
		"timestamp": 1740988402000,
		"items": {
			"14": -68.0,
			"0": 21,
			"13": 12581,
			"16": -75.0,
			"17": 12588,
			"3": 11.3,
			"18": -76.0,
			"1": 113.985946,
			"2": 100.0,
			"12": -65.0,
			"15": 12570,
			"11": 12589
		}
	},
	{
		"mac": "0004fbf4ea0f",
		"kind": 17,
		"timestamp": 1740988405000,
		"items": {
			"2": 100.0,
			"16": -72.0,
			"3": 11.3,
			"18": -73.0,
			"11": 12581,
			"12": -67.0,
			"13": 12589,
			"14": -69.0,
			"17": 12572,
			"0": 21,
			"15": 12580,
			"1": 113.985946
		}
	},
	{
		"mac": "0004fbf4ea0f",
		"kind": 17,
		"timestamp": 1740988408000,
		"items": {
			"14": -65.0,
			"0": 21,
			"11": 12589,
			"12": -59.0,
			"15": 12581,
			"3": 11.3,
			"16": -65.0,
			"2": 100.0,
			"1": 113.985946,
			"17": 12588,
			"18": -76.0,
			"13": 12577
		}
	},
	{
		"mac": "0004fbf4ea0f",
		"kind": 17,
		"timestamp": 1740988411000,
		"items": {
			"11": 12589,
			"2": 100.0,
			"12": -58.0,
			"13": 12581,
			"16": -71.0,
			"3": 11.3,
			"18": -75.0,
			"0": 21,
			"17": 16523,
			"15": 12572,
			"14": -59.0,
			"1": 113.985946
		}
	},
	{
		"mac": "0004fbf4ea0f",
		"kind": 17,
		"timestamp": 1740988414000,
		"items": {
			"18": -71.0,
			"15": 12589,
			"0": 21,
			"13": 12577,
			"2": 100.0,
			"1": 113.985946,
			"11": 12581,
			"16": -66.0,
			"14": -65.0,
			"17": 12572,
			"3": 11.3,
			"12": -64.0
		}
	},
	{
		"mac": "0004fbf4ea0f",
		"kind": 17,
		"timestamp": 1740988417000,
		"items": {
			"1": 113.985948,
			"14": -64.0,
			"17": 12572,
			"0": 21,
			"3": 11.3,
			"15": 12589,
			"16": -71.0,
			"18": -74.0,
			"2": 100.0,
			"12": -60.0,
			"13": 12577,
			"11": 12581
		}
	},
	{
		"mac": "0004fbf4ea0f",
		"kind": 17,
		"timestamp": 1740988420000,
		"items": {
			"11": 12577,
			"2": 100.0,
			"18": -75.0,
			"13": 12581,
			"3": 11.3,
			"1": 113.985948,
			"15": 12572,
			"14": -65.0,
			"12": -65.0,
			"16": -68.0,
			"17": 12580,
			"0": 21
		}
	},
	{
		"mac": "0004fbf4ea0f",
		"kind": 17,
		"timestamp": 1740988423000,
		"items": {
			"16": -69.0,
			"18": -70.0,
			"0": 21,
			"3": 11.3,
			"14": -68.0,
			"2": 100.0,
			"15": 12581,
			"11": 12572,
			"17": 12577,
			"13": 12588,
			"12": -68.0,
			"1": 113.985948
		}
	},
	{
		"mac": "0004fbf4ea0f",
		"kind": 17,
		"timestamp": 1740988426000,
		"items": {
			"15": 12572,
			"14": -68.0,
			"0": 21,
			"17": 12588,
			"12": -66.0,
			"16": -71.0,
			"1": 113.985955,
			"13": 12577,
			"18": -72.0,
			"11": 12580,
			"3": 11.1,
			"2": 100.0
		}
	},
	{
		"mac": "0004fbf4ea0f",
		"kind": 17,
		"timestamp": 1740988430000,
		"items": {
			"17": 12572,
			"11": 12577,
			"18": -71.0,
			"13": 12580,
			"16": -69.0,
			"0": 21,
			"3": 11.1,
			"15": 12588,
			"1": 113.985957,
			"2": 100.0,
			"12": -65.0,
			"14": -68.0
		}
	},
	{
		"mac": "0004fbf4ea0f",
		"kind": 17,
		"timestamp": 1740988433000,
		"items": {
			"1": 113.985958,
			"14": -68.0,
			"15": 12577,
			"11": 12588,
			"13": 12580,
			"16": -71.0,
			"12": -58.0,
			"18": -76.0,
			"0": 21,
			"3": 11.1,
			"2": 100.0,
			"17": 12572
		}
	},
	{
		"mac": "0004fbf4ea0f",
		"kind": 17,
		"timestamp": 1740988436000,
		"items": {
			"1": 113.985959,
			"16": -71.0,
			"12": -68.0,
			"2": 100.0,
			"15": 12572,
			"17": 12577,
			"14": -68.0,
			"11": 12588,
			"18": -74.0,
			"13": 12580,
			"0": 21,
			"3": 11.1
		}
	},
	{
		"mac": "0004fbf4ea0f",
		"kind": 17,
		"timestamp": 1740988439000,
		"items": {
			"18": -76.0,
			"16": -72.0,
			"0": 21,
			"3": 11.1,
			"14": -67.0,
			"15": 12572,
			"13": 12580,
			"11": 12577,
			"1": 113.985957,
			"12": -65.0,
			"2": 100.0,
			"17": 12589
		}
	},
	{
		"mac": "0004fbf4ea0f",
		"kind": 17,
		"timestamp": 1740988442000,
		"items": {
			"0": 21,
			"16": -74.0,
			"18": -74.0,
			"13": 12576,
			"12": -63.0,
			"2": 100.0,
			"17": 12572,
			"14": -73.0,
			"1": 113.985958,
			"15": 12588,
			"3": 11.1,
			"11": 12580
		}
	},
	{
		"mac": "0004fbf4ea0f",
		"kind": 17,
		"timestamp": 1740988445000,
		"items": {
			"11": 12580,
			"18": -77.0,
			"12": -66.0,
			"17": 12581,
			"14": -69.0,
			"2": 100.0,
			"16": -75.0,
			"1": 113.98596,
			"0": 21,
			"3": 11.1,
			"15": 12572,
			"13": 12588
		}
	},
	{
		"mac": "0004fbf4ea0f",
		"kind": 17,
		"timestamp": 1740988448000,
		"items": {
			"12": -65.0,
			"17": 12577,
			"16": -77.0,
			"13": 12580,
			"11": 12576,
			"2": 100.0,
			"3": 11.1,
			"18": -78.0,
			"14": -77.0,
			"15": 12581,
			"1": 113.98596,
			"0": 21
		}
	},
	{
		"mac": "0004fbf4ea0f",
		"kind": 17,
		"timestamp": 1740988451000,
		"items": {
			"3": 11.1,
			"11": 12576,
			"12": -63.0,
			"16": -74.0,
			"2": 100.0,
			"15": 12580,
			"17": 12577,
			"13": 12572,
			"18": -76.0,
			"14": -73.0,
			"0": 21,
			"1": 113.98596
		}
	},
	{
		"mac": "0004fbf4ea0f",
		"kind": 17,
		"timestamp": 1740988454000,
		"items": {
			"2": 100.0,
			"3": 11.0,
			"0": 21,
			"14": -77.0,
			"15": 12577,
			"13": 12580,
			"16": -78.0,
			"1": 113.985963,
			"12": -73.0,
			"18": -78.0,
			"17": 12576,
			"11": 12588
		}
	},
	{
		"mac": "0004fbf4ea0f",
		"kind": 17,
		"timestamp": 1740988458000,
		"items": {
			"18": -77.0,
			"15": 12577,
			"3": 10.9,
			"13": 12572,
			"2": 100.0,
			"11": 12581,
			"17": 12580,
			"1": 113.985963,
			"0": 21,
			"12": -72.0,
			"16": -74.0,
			"14": -73.0
		}
	},
	{
		"mac": "0004fbf4ea0f",
		"kind": 17,
		"timestamp": 1740988461000,
		"items": {
			"12": -74.0,
			"1": 113.985964,
			"0": 21,
			"15": 12588,
			"17": 12581,
			"2": 100.0,
			"14": -77.0,
			"3": 10.8,
			"18": -79.0,
			"13": 12587,
			"11": 12572,
			"16": -78.0
		}
	},
	{
		"mac": "0004fbf4ea0f",
		"kind": 17,
		"timestamp": 1740988464000,
		"items": {
			"13": 12588,
			"11": 12587,
			"15": 12577,
			"0": 21,
			"16": -80.0,
			"2": 100.0,
			"17": 12589,
			"3": 11.0,
			"14": -72.0,
			"12": -65.0,
			"1": 113.985962,
			"18": -80.0
		}
	},
	{
		"mac": "0004fbf4ea0f",
		"kind": 17,
		"timestamp": 1740988467000,
		"items": {
			"3": 10.9,
			"11": 12587,
			"2": 100.0,
			"0": 21,
			"12": -60.0,
			"14": -75.0,
			"13": 12589,
			"1": 113.985963,
			"16": -80.0,
			"15": 12572,
			"17": 12576,
			"18": -84.0
		}
	},
	{
		"mac": "0004fbf4ea0f",
		"kind": 17,
		"timestamp": 1740988470000,
		"items": {
			"18": -81.0,
			"17": 12577,
			"3": 10.9,
			"11": 12587,
			"12": -72.0,
			"14": -73.0,
			"1": 113.985962,
			"13": 12589,
			"0": 21,
			"15": 12581,
			"2": 100.0,
			"16": -80.0
		}
	},
	{
		"mac": "0004fbf4ea0f",
		"kind": 17,
		"timestamp": 1740988473000,
		"items": {
			"0": 21,
			"13": 12589,
			"14": -75.0,
			"16": -80.0,
			"3": 10.9,
			"12": -68.0,
			"2": 100.0,
			"17": 12580,
			"1": 113.98596,
			"15": 12581,
			"11": 12587,
			"18": -81.0
		}
	},
	{
		"mac": "0004fbf4ea0f",
		"kind": 17,
		"timestamp": 1740988476000,
		"items": {
			"14": -71.0,
			"13": 12589,
			"12": -71.0,
			"11": 12587,
			"1": 113.98596,
			"2": 100.0,
			"3": 10.9,
			"15": 12574,
			"17": 12581,
			"0": 21,
			"16": -74.0,
			"18": -74.0
		}
	},
	{
		"mac": "0004fbf4ea0f",
		"kind": 17,
		"timestamp": 1740988479000,
		"items": {
			"3": 10.9,
			"0": 21,
			"14": -64.0,
			"13": 12582,
			"17": 12571,
			"1": 113.985964,
			"2": 100.0,
			"11": 12578,
			"15": 12570,
			"16": -65.0,
			"18": -65.0,
			"12": -62.0
		}
	},
	{
		"mac": "0004fbf4ea0f",
		"kind": 17,
		"timestamp": 1740988482000,
		"items": {
			"14": -65.0,
			"15": 16533,
			"18": -68.0,
			"3": 10.9,
			"17": 16523,
			"13": 12578,
			"12": -60.0,
			"2": 100.0,
			"1": 113.985964,
			"16": -68.0,
			"0": 21,
			"11": 12571
		}
	},
	{
		"mac": "0004fbf4ea0f",
		"kind": 17,
		"timestamp": 1740988486000,
		"items": {
			"2": 100.0,
			"3": 10.9,
			"11": 16524,
			"12": -65.0,
			"15": 16523,
			"16": -71.0,
			"18": -72.0,
			"13": 16533,
			"0": 21,
			"1": 113.985965,
			"14": -71.0,
			"17": 16515
		}
	},
	{
		"mac": "0004fbf4ea0f",
		"kind": 17,
		"timestamp": 1740988489000,
		"items": {
			"14": -68.0,
			"0": 21,
			"12": -66.0,
			"11": 16533,
			"3": 10.9,
			"16": -74.0,
			"18": -74.0,
			"13": 16524,
			"1": 113.985965,
			"15": 12575,
			"2": 100.0,
			"17": 12583
		}
	},
	{
		"mac": "0004fbf4ea0f",
		"kind": 17,
		"timestamp": 1740988492000,
		"items": {
			"12": -60.0,
			"3": 10.9,
			"14": -65.0,
			"17": 16515,
			"2": 100.0,
			"11": 16523,
			"0": 21,
			"1": 113.985965,
			"18": -73.0,
			"15": 12583,
			"16": -71.0,
			"13": 12575
		}
	},
	{
		"mac": "0004fbf4ea0f",
		"kind": 17,
		"timestamp": 1740988495000,
		"items": {
			"16": -76.0,
			"18": -77.0,
			"12": -64.0,
			"17": 16523,
			"11": 12583,
			"1": 113.985965,
			"3": 10.9,
			"0": 21,
			"13": 16524,
			"2": 100.0,
			"14": -69.0,
			"15": 16533
		}
	}
]